GdipBianchengJichu/README.md
GdipBianchengJichu/__init__.py
GdipBianchengJichu/__main__.py
GdipBianchengJichu/file.epub
GdipBianchengJichu/index.html
GdipBianchengJichu/css/__init__.py
GdipBianchengJichu/css/annotations.css
GdipBianchengJichu/css/main.css
GdipBianchengJichu/css/normalize.css
GdipBianchengJichu/css/popup.css
GdipBianchengJichu/font/__init__.py
GdipBianchengJichu/font/fontello.eot
GdipBianchengJichu/font/fontello.svg
GdipBianchengJichu/font/fontello.ttf
GdipBianchengJichu/font/fontello.woff
GdipBianchengJichu/img/__init__.py
GdipBianchengJichu/img/annotator-glyph-sprite.png
GdipBianchengJichu/img/annotator-icon-sprite.png
GdipBianchengJichu/img/apple-touch-icon.png
GdipBianchengJichu/img/cancelfullscreen.png
GdipBianchengJichu/img/close.png
GdipBianchengJichu/img/fullscreen.png
GdipBianchengJichu/img/loader.gif
GdipBianchengJichu/img/menu-icon.png
GdipBianchengJichu/img/save.png
GdipBianchengJichu/img/saved.png
GdipBianchengJichu/img/settings-s.png
GdipBianchengJichu/img/settings.png
GdipBianchengJichu/img/star.png
GdipBianchengJichu/js/__init__.py
GdipBianchengJichu/js/epub.js
GdipBianchengJichu/js/epub.min.js
GdipBianchengJichu/js/epub.min.map
GdipBianchengJichu/js/hooks.min.js
GdipBianchengJichu/js/hooks.min.map
GdipBianchengJichu/js/reader.js
GdipBianchengJichu/js/reader.js.map
GdipBianchengJichu/js/reader.min.js
GdipBianchengJichu/js/reader.min.map
GdipBianchengJichu/js/hooks/__init__.py
GdipBianchengJichu/js/hooks/extensions/__init__.py
GdipBianchengJichu/js/hooks/extensions/highlight.js
GdipBianchengJichu/js/libs/__init__.py
GdipBianchengJichu/js/libs/jquery.min.js
GdipBianchengJichu/js/libs/localforage.min.js
GdipBianchengJichu/js/libs/screenfull.js
GdipBianchengJichu/js/libs/screenfull.min.js
GdipBianchengJichu/js/libs/zip.min.js
GdipBianchengJichu/js/plugins/__init__.py
GdipBianchengJichu/js/plugins/hypothesis.js
GdipBianchengJichu/js/plugins/search.js
gdip_biancheng_jichu-2024.3.1.0.dist-info/METADATA
gdip_biancheng_jichu-2024.3.1.0.dist-info/WHEEL
gdip_biancheng_jichu-2024.3.1.0.dist-info/entry_points.txt
gdip_biancheng_jichu-2024.3.1.0.dist-info/top_level.txt
gdip_biancheng_jichu-2024.3.1.0.dist-info/RECORD
